al360_trustworthyai_text/__init__.py
al360_trustworthyai_text/version.py
al360_trustworthyai_text/common/__init__.py
al360_trustworthyai_text/common/constants.py
al360_trustworthyai_text/managers/__init__.py
al360_trustworthyai_text/managers/error_analysis_manager.py
al360_trustworthyai_text/managers/explainer_manager.py
al360_trustworthyai_text/rai_text_insights/__init__.py
al360_trustworthyai_text/rai_text_insights/rai_text_insights.py
al360_trustworthyai_text/utils/__init__.py
al360_trustworthyai_text/utils/feature_extractors.py
al360_trustworthyai_text/utils/question_answering.py
al360_trustworthyai_text/utils/genai_metrics/__init__.py
al360_trustworthyai_text/utils/genai_metrics/constants.py
al360_trustworthyai_text/utils/genai_metrics/metrics.py
al360_trustworthyai_text/utils/genai_metrics/scripts/__init__.py
al360_trustworthyai_text/utils/genai_metrics/scripts/_compute.py
al360_trustworthyai_text/utils/genai_metrics/scripts/coherence.py
al360_trustworthyai_text/utils/genai_metrics/scripts/equivalence.py
al360_trustworthyai_text/utils/genai_metrics/scripts/fluency.py
al360_trustworthyai_text/utils/genai_metrics/scripts/groundedness.py
al360_trustworthyai_text/utils/genai_metrics/scripts/relevance.py
al360_trustworthyai_text-0.2.7.dist-info/METADATA
al360_trustworthyai_text-0.2.7.dist-info/WHEEL
al360_trustworthyai_text-0.2.7.dist-info/top_level.txt
al360_trustworthyai_text-0.2.7.dist-info/RECORD
