Metadata-Version: 2.1
Name: al360_trustworthyai_text
Version: 0.2.7
Summary: SDK API to assess text Machine Learning models.
Home-page: https://github.com/affectlog360/affectlog360
Author: Roman Lutz, Ilya Matiach, Ke Xu
Author-email: al360_taiwidgets-maintain@affectlog.com
Classifier: Programming Language :: Python :: 3.7
Classifier: Programming Language :: Python :: 3.8
Classifier: Programming Language :: Python :: 3.9
Classifier: License :: OSI Approved :: MIT License
Classifier: Operating System :: OS Independent
Classifier: Development Status :: 3 - Alpha
Requires-Python: >=3.7
Requires-Dist: numpy<2.0.0,>=1.17.2
Requires-Dist: pandas>=0.25.1
Requires-Dist: scikit-learn>=0.22.1
Requires-Dist: scipy>=1.4.1
Requires-Dist: semver~=2.13.0
Requires-Dist: nlp-feature-extractors==0.1.0
Requires-Dist: al360-trustworthyai>=0.35.0
Provides-Extra: generative_text
Requires-Dist: interpret-text; extra == "generative-text"
Requires-Dist: sentence-transformers; extra == "generative-text"
Provides-Extra: qa
Requires-Dist: evaluate; extra == "qa"
Requires-Dist: bert-score; extra == "qa"
Requires-Dist: nltk; extra == "qa"
Requires-Dist: rouge-score; extra == "qa"
